pytimbr_api/__init__.py
pytimbr_api/timbr_http_connector.py
pytimbr_api-2.0.0.dist-info/licenses/LICENSE
pytimbr_api-2.0.0.dist-info/METADATA
pytimbr_api-2.0.0.dist-info/WHEEL
pytimbr_api-2.0.0.dist-info/top_level.txt
pytimbr_api-2.0.0.dist-info/RECORD
