Metadata-Version: 2.4
Name: pytimbr_api
Version: 2.0.0
Summary: Timbr REST API connector
Author-email: timbr <contact@timbr.ai>
Maintainer-email: timbr <contact@timbr.ai>
License-Expression: MIT
Project-URL: Homepage, https://github.com/WPSemantix/timbr_python_http
Project-URL: Download, https://github.com/WPSemantix/timbr_python_http/archive/refs/tags/v1.0.10.tar.gz
Project-URL: Bug Tracker, https://github.com/WPSemantix/timbr_python_http/issues
Project-URL: Repository, https://github.com/WPSemantix/timbr_python_http
Keywords: timbr,timbr-http,timbr-https,timbr-rest,timbr-api,timbr-rest-api,timbr-connector,PyTimbrRestAPI,PyTimbr,pytimbrapi,PyTimbrAPI,pytimbr_api,PyTimbr_API
Classifier: Development Status :: 5 - Production/Stable
Classifier: Intended Audience :: Developers
Classifier: Topic :: Software Development :: Build Tools
Classifier: Programming Language :: Python :: 3
Classifier: Programming Language :: Python :: 3.9
Classifier: Programming Language :: Python :: 3.10
Classifier: Programming Language :: Python :: 3.11
Classifier: Programming Language :: Python :: 3.12
Requires-Python: >=3.9
License-File: LICENSE
Requires-Dist: requests>=2.32.4
Dynamic: license-file
